FlightStream/__init__.py
FlightStream/__main__.py
FlightStream/Assets/__init__.py
FlightStream/abstract/__init__.py
FlightStream/abstract/page_template.py
FlightStream/abstract/page_template_xl.py
FlightStream/abstract/thread_abstract.py
FlightStream/actions/__init__.py
FlightStream/actions/abstract_action.py
FlightStream/actions/action_event.py
FlightStream/actions/action_event_change_degrees.py
FlightStream/actions/action_event_increment.py
FlightStream/actions/action_property.py
FlightStream/actions/action_property_change.py
FlightStream/actions/action_property_degrees.py
FlightStream/actions/action_property_toggle.py
FlightStream/button_types/__init__.py
FlightStream/button_types/button.py
FlightStream/button_types/button_event.py
FlightStream/button_types/button_function.py
FlightStream/button_types/button_monitor.py
FlightStream/button_types/button_monitor_indicator.py
FlightStream/buttons/ButtonPushback.py
FlightStream/buttons/__init__.py
FlightStream/buttons/airspeed_true.py
FlightStream/buttons/altitude.py
FlightStream/buttons/button_exit.py
FlightStream/buttons/button_flight_level.py
FlightStream/buttons/button_flight_level_change.py
FlightStream/buttons/button_throttle.py
FlightStream/buttons/camera_state.py
FlightStream/buttons/camera_view_type_index.py
FlightStream/buttons/ground_speed.py
FlightStream/buttons/set_heading.py
FlightStream/fonts/24003_LucidaGrande.ttf
FlightStream/fonts/__init__.py
FlightStream/page_buttons/__init__.py
FlightStream/page_buttons/button_page.py
FlightStream/page_buttons/button_page_home.py
FlightStream/page_buttons/button_page_home_inactive.py
FlightStream/page_buttons/button_page_inactive.py
FlightStream/page_buttons/button_page_startup.py
FlightStream/page_buttons/button_page_startup_inactive.py
FlightStream/page_buttons/button_page_takeoff_land.py
FlightStream/page_buttons/button_page_takeoff_land_inactive.py
FlightStream/page_buttons/button_page_views.py
FlightStream/page_buttons/button_page_views_inactive.py
FlightStream-0.0.802.dist-info/METADATA
FlightStream-0.0.802.dist-info/WHEEL
FlightStream-0.0.802.dist-info/license.txt
FlightStream-0.0.802.dist-info/top_level.txt
FlightStream-0.0.802.dist-info/zip-safe
FlightStream-0.0.802.dist-info/RECORD
