Metadata-Version: 2.1
Name: FlightStream
Version: 0.0.802
Summary: Integrate StreamDeck with Microsoft Flight Simulator
Author: "Ligasy"
Author-email: Ligasy <author@example.com>
Project-URL: Homepage, https://github.com/pypa/flightstream
Project-URL: Bug Tracker, https://github.com/pypa/flightstream/issues
Classifier: Programming Language :: Python :: 3
Classifier: License :: OSI Approved :: MIT License
Classifier: Operating System :: OS Independent
Requires-Python: >=3.7
License-File: license.txt
Requires-Dist: Pillow (>=9.0.0)
Requires-Dist: SimConnect (>=0.4.23)
Requires-Dist: streamdeck (>=0.9.0)
